MANIFEST.in
README.rst
VERSION.txt
requirements.txt
setup.py
mlbox/__init__.py
mlbox.egg-info/PKG-INFO
mlbox.egg-info/SOURCES.txt
mlbox.egg-info/dependency_links.txt
mlbox.egg-info/not-zip-safe
mlbox.egg-info/requires.txt
mlbox.egg-info/top_level.txt
mlbox/encoding/__init__.py
mlbox/encoding/categorical_encoder.py
mlbox/encoding/na_encoder.py
mlbox/model/__init__.py
mlbox/model/classification/__init__.py
mlbox/model/classification/classifier.py
mlbox/model/classification/feature_selector.py
mlbox/model/classification/stacking_classifier.py
mlbox/model/regression/__init__.py
mlbox/model/regression/feature_selector.py
mlbox/model/regression/regressor.py
mlbox/model/regression/stacking_regressor.py
mlbox/optimisation/__init__.py
mlbox/optimisation/optimiser.py
mlbox/prediction/__init__.py
mlbox/prediction/predictor.py
mlbox/preprocessing/__init__.py
mlbox/preprocessing/drift_thresholder.py
mlbox/preprocessing/reader.py
mlbox/preprocessing/drift/__init__.py
mlbox/preprocessing/drift/drift_estimator.py
mlbox/preprocessing/drift/drift_threshold.py