Metadata-Version: 1.1
Name: mlbox
Version: 0.8.1
Summary: A powerful Automated Machine Learning python library.
Home-page: https://github.com/AxeldeRomblay/mlbox
Author: Axel ARONIO DE ROMBLAY
Author-email: axelderomblay@gmail.com
License: BSD-3
Keywords: mlbox auto-ml stacking pipeline optimisation
Platform: UNKNOWN
Classifier: Development Status :: 5 - Production/Stable
Classifier: Intended Audience :: Developers
Classifier: Intended Audience :: Science/Research
Classifier: Topic :: Scientific/Engineering :: Artificial Intelligence
Classifier: Topic :: Scientific/Engineering :: Information Analysis
Classifier: Topic :: Software Development :: Libraries :: Python Modules
Classifier: License :: OSI Approved :: BSD License
Classifier: Natural Language :: English
Classifier: Operating System :: MacOS
Classifier: Operating System :: Microsoft :: Windows
Classifier: Operating System :: POSIX :: Linux
Classifier: Programming Language :: Python :: 3.5
Classifier: Programming Language :: Python :: 3.6
Classifier: Programming Language :: Python :: 3.7
